[{"conv_id": 9511, "domain": "movies", "seed_entity": "https://www.wikidata.org/wiki/Q155476", "seed_entity_text": "The Fast and the Furious", "questions": [{"question_id": "9511-0", "question": "On which day was the 2001 movie The Fast and the Furious originally released?", "turn": 0, "answer": "22 June 2001", "answer_text": "22 June 2001", "given_answers": ["The\u202fFast\u202fand\u202fthe\u202fFurious premiered in the United States on **Friday,\u202fJune\u202f22,\u202f2001**.", "The Fast and the Furious was originally released on **June\u202f22,\u202f2001**.", "The 2001 film **_The Fast and the Furious_** was originally released in theaters on **June\u202f22,\u202f2001**."], "latencies": [0.5353801250457764, 0.3495450019836426, 0.32957959175109863]}, {"question_id": "9511-1", "question": "Who plays Dominic Toretto?", "turn": 1, "answer": "https://www.wikidata.org/wiki/Q178166", "answer_text": "Vin Diesel", "completed_question": "Which actor plays the role of Dominic Toretto in the film The Fast and the Furious?", "given_answers": ["Dominic\u202fToretto is portrayed by **Vin\u202fDiesel** (born Mark\u202fVincent\u202fVincent) in the *Fast\u202f&\u202fFurious* franchise. He has played the character in every film of the series (except for a brief cameo in *Fast\u202f&\u202fFurious\u202f7* where his scenes were filled in with stand\u2011ins after Diesel\u2019s injury).", "Dominic \u201cDom\u201d Toretto is portrayed by **Vin\u202fDiesel** (born Mark Sinclair) in the *Fast &\u202fFurious* film series. He has played the character in every main installment since the franchise\u2019s debut in 2001.", "Dominic\u202fToretto is portrayed by **Vin Diesel**."], "latencies": [0.3521292209625244, 0.34342145919799805, 0.2062826156616211]}, {"question_id": "9511-2", "question": "What number of these movies were made?", "turn": 2, "answer": "10", "answer_text": "10", "completed_question": "How many total films were made in The Fast and the Furious series?", "given_answers": ["**Main\u2011line \u201cFast &\u202fFurious\u201d films (the saga that follows Dominic\u202fToretto\u2019s story)**  \n\n| # | Title (U.S. release year) | Release date (U.S.) |\n|---|----------------------------|----------------------|\n| 1 | *The Fast and the Furious* (2001) | June\u202f22\u202f2001 |\n| 2 | *2 Fast\u202f2\u202fFurious* (2003) | June\u202f6\u202f2003 |\n| 3 | *The Fast and the Furious: Tokyo\u202fDrift* (2006) | June\u202f16\u202f2006 |\n| 4 | *Fast\u202f&\u202fFurious* (2009) | April\u202f3\u202f2009 |\n| 5 | *Fast\u202fFive* (2011) | April\u202f29\u202f2011 |\n| 6 | *Fast\u202f&\u202fFurious\u202f6* (2013) | May\u202f24\u202f2013 |\n| 7 | *Furious\u202f7* (2015) | April\u202f3\u202f2015 |\n| 8 | *The Fate of the Furious* (2017) | April\u202f14\u202f2017 |\n| 9 | *F9* (2021) | June\u202f25\u202f2021 |\n|10 | *Fast\u202fX* (2023) | May\u202f19\u202f2023 |\n|11 | *Fast\u202fX: Part\u202f2* (2025) | May\u202f24\u202f2025 |\n\n### So, **eleven** main\u2011line \u201cFast &\u202fFurious\u201d movies have been released (the eleventh, *Fast\u202fX: Part\u202f2*, arrived in 2025).  \n\nIf you also count the official spin\u2011off:\n\n| # | Spin\u2011off title | Release year |\n|---|----------------|--------------|\n| 1 | *Fast &\u202fFurious Presents: Hobbs\u202f&\u202fShaw* | August\u202f2021 |\n\nIncluding that spin\u2011off would bring the total number of theatrical releases in the franchise to **twelve**.  \n\n*(All dates are U.S. theatrical releases.)*", "**Total films released in the *Fast\u202f&\u202fFurious* franchise (up to 2026):\u202f12**\n\n| # | Title (Year) | Type |\n|---|--------------|------|\n| 1 | *The Fast and the Furious* (2001) | Main series |\n| 2 | *2 Fast 2 Furious* (2003) | Main series |\n| 3 | *The Fast and the Furious: Tokyo Drift* (2006) | Main series |\n| 4 | *Fast & Furious* (2009) | Main series |\n| 5 | *Fast Five* (2011) | Main series |\n| 6 | *Fast & Furious 6* (2013) | Main series |\n| 7 | *Furious 7* (2015) | Main series |\n| 8 | *The Fate of the Furious* (2017) | Main series |\n| 9 | *Fast & Furious Presents: Hobbs\u202f&\u202fShaw* (2019) | Spin\u2011off |\n|10| *F9* (2021) | Main series |\n|11| *Fast X* (2023) | Main series (first part) |\n|12| *Fast X: Part\u202f2* (2025) | Main series (second part) |\n\nSo, counting all theatrical releases\u2014including the spin\u2011off *Hobbs\u202f&\u202fShaw* and the two\u2011part finale *Fast\u202fX*\u2014the franchise has **12 movies** released to date.", "As of today (April\u202f2026), the **_Fast\u202f&\u202fFurious_** franchise has had **eleven** theatrical films released:\n\n| # | Title | Release Year | Note |\n|---|----------------------------------------------|--------------|-----------------------|\n| 1 | **The Fast and the Furious** | 2001 | Original film |\n| 2 | **2\u202fFast\u202f2\u202fFurious** | 2003 | Direct sequel |\n| 3 | **The Fast and the Furious: Tokyo\u202fDrift** | 2006 | Third installment |\n| 4 | **Fast & Furious** | 2009 | Fourth installment |\n| 5 | **Fast Five** | 2011 | Fifth installment |\n| 6 | **Fast & Furious\u202f6** | 2013 | Sixth installment |\n| 7 | **Furious\u202f7** | 2015 | Seventh installment |\n| 8 | **The Fate of the Furious** | 2017 | Eighth installment |\n| 9 | **F9 (Fast\u202f9)** | 2021 | Ninth installment |\n|10| **Fast\u202f&\u202fFurious Presents: Hobbs\u202f&\u202fShaw** | 2021 | First spin\u2011off (still a theatrical release) |\n|11| **Fast\u202fX** | 2023 | Tenth main\u2011series entry |\n\nA sequel to **Fast\u202fX** (often referred to as \u201cFast\u202fX \u2013 Part\u202f2\u201d) is scheduled for release in 2025, which would bring the total to **twelve** films once it hits theaters. But up to the current date, **eleven** movies have been released."], "latencies": [1.659010410308838, 1.6442553997039795, 1.8510301113128662]}, {"question_id": "9511-3", "question": "What's the name of the movie's director?", "turn": 3, "answer": "https://www.wikidata.org/wiki/Q503966", "answer_text": "Rob Cohen", "completed_question": "What is the name of the person who directed the 2001 film The Fast and the Furious?", "given_answers": ["The 2001 film **\u201cThe\u202fFast\u202fand\u202fthe\u202fFurious\u201d** was directed by **Rob\u202fCohen**.", "The 2001 film **\u201cThe\u202fFast\u202fand\u202fthe\u202fFurious\u201d** was directed by **Rob\u202fCohen**.", "The 2001 film **_The Fast and the Furious_** was directed by **Rob\u202fCohen**."], "latencies": [0.4666249752044678, 0.34681200981140137, 0.2793152332305908]}, {"question_id": "9511-4", "question": "Did he direct Stealth?", "turn": 4, "answer": "yes", "answer_text": "yes", "completed_question": "Did Rob Cohen direct the 2005 film Stealth?", "given_answers": ["Yes.\u202fRob\u202fCohen was also the director of **\u201cStealth\u201d** (the 2005 science\u2011fiction action film starring Jamie\u202fFoxx, Jessica\u202fAlba and Stellan\u202fSkarsg\u00e5rd). The movie was released in early 2005 and, like *The\u202fFast\u202fand\u202fthe\u202fFurious*, was a big\u2011budget action\u2011oriented project that Cohen helmed.", "Yes. **Rob\u202fCohen** directed the 2005 sci\u2011fi action film **\u201cStealth.\u201d** The movie stars **Jessica\u202fSimpson, Jamie\u202fFoxx,** and **Josh\u202fDuhamel**, and follows a trio of fighter pilots who must stop a rogue, AI\u2011controlled stealth aircraft. It was released in the United States on January\u202f28\u202f2005.", "Yes.\u202fRob\u202fCohen also directed the 2005 science\u2011fiction action film **_Stealth_** (starring Jessica\u202fAlba, Josh\u202fDuhamel, and Jamie\u202fFoxx). The movie was released in August\u202f2005 and is part of Cohen\u2019s repertoire of high\u2011octane, effects\u2011driven films."], "latencies": [0.4876515865325928, 0.4847850799560547, 0.5497879981994629]}]}, {"conv_id": 9219, "domain": "soccer", "seed_entity": "https://www.wikidata.org/wiki/Q615", "seed_entity_text": "Lionel Messi", "questions": [{"question_id": "9219-0", "question": "Where does Lionel Messi come from?", "turn": 0, "answer": "https://www.wikidata.org/wiki/Q414", "answer_text": "Argentina", "given_answers": ["Lionel\u202fMessi was born in **Rosario, Argentina** on June\u202f24\u202f1987. He grew up in the city of Rosario before moving to Spain as a teenager to join FC\u202fBarcelona\u2019s famed youth academy, La\u202fMasia. His Argentine roots remain a big part of his identity, and he has represented Argentina\u2019s national team throughout his career.", "Lionel\u202fMessi was born in **Rosario, Santa\u202fFe Province, Argentina** on June\u202f24\u202f1987. He grew up there before moving to Spain as a teenager to join FC\u202fBarcelona\u2019s youth academy, La\u202fMasia. While he has spent much of his professional career in Europe (Spain and later France), his national team allegiance has always been with Argentina, and he has captained the Argentine national side to major trophies such as the Copa\u202fAmerica (2021) and the FIFA\u202fWorld Cup (2022).", "Lionel\u202fMessi was born in **Rosario, Argentina** (specifically, in the city\u2019s Barrio Villa\u202fDom\u00ednico on June\u202f24\u202f1987). He grew up there before moving to Spain to join FC\u202fBarcelona\u2019s youth academy."], "latencies": [0.35052490234375, 2.483170509338379, 4.356592178344727]}, {"question_id": "9219-1", "question": "and when was he born?", "turn": 1, "answer": "24 June 1987", "answer_text": "24 June 1987", "completed_question": "When was the soccer player Lionel Messi born?", "given_answers": ["Lionel\u202fMessi was born on **June\u202f24\u202f1987** (24\u202fJune\u202f1987).", "Lionel\u202fMessi was born on **June\u202f24\u202f1987**.", "Lionel\u202fMessi was born on **June\u202f24\u202f1987**."], "latencies": [1.334204912185669, 0.22778964042663574, 2.2826685905456543]}, {"question_id": "9219-2", "question": "where was he born?", "turn": 2, "answer": "https://www.wikidata.org/wiki/Q52535", "answer_text": "Rosario", "completed_question": "In what city was the soccer player Lionel Messi born?", "given_answers": ["Lionel\u202fMessi was born in **Rosario, Argentina**.", "Lionel\u202fMessi was born in **Rosario**, a city in the **Santa\u202fFe Province of Argentina**.", "Lionel\u202fMessi was born in **Rosario, Argentina**, on June\u202f24\u202f1987. He entered the world at the **Hospital Privado San\u202fLorenzo** in the city's Villa\u202fDom\u00ednico neighborhood."], "latencies": [0.196333646774292, 4.373970985412598, 0.28295040130615234]}, {"question_id": "9219-3", "question": "does he have a wife?", "turn": 3, "answer": "yes", "answer_text": "yes", "completed_question": "Is the soccer player Lionel Messi married?", "given_answers": ["Yes. Lionel\u202fMessi is married to **Antonella Roccuzzo**. \n\n- **How they met:** They grew up together in Rosario, Argentina, and have known each other since childhood.  \n- **Marriage:** They were married on **June\u202f30\u202f2017** in a ceremony in their hometown of Rosario.  \n- **Family:** The couple have three sons\u2014Thiago (born\u202f2012), Mateo (born\u202f2015) and Ciro (born\u202f2018).  \n\nAntonella is often seen supporting Messi at matches and events, and she runs her own business ventures, including a fashion line and a skincare brand.", "Yes. Lionel\u202fMessi is married to **Antonela\u202fRoccuzzo**.  \n\n- **How they met:** They grew up together in Rosario and have known each other since childhood.  \n- **Marriage:** They were married in a private ceremony in Rosario on **June\u202f30\u202f2017**.  \n- **Family:** The couple has three children\u2014Thiago (born\u202f2012), Mateo (born\u202f2015), and Ciro (born\u202f2018).  \n\nAntonela Roccuzzo is often seen supporting Messi at matches and is active on social media, where she shares glimpses of their family life.", "Yes. Lionel\u202fMessi is married to **Antonella Roccuzzo**.  \n\n- **How they met:** They grew up together in Rosario; Antonella is a cousin of Messi\u2019s childhood friend\u202fLu\u00eds\u202fSu\u00e1rez.  \n- **Engagement & marriage:** They announced their engagement in June\u202f2017 and were married on **30\u202fJune\u202f2017** in a ceremony in Rosario, Argentina.  \n- **Family:** The couple has three children\u2014Thiago (born\u202f2012), Mateo (born\u202f2015) and Ciro (born\u202f2018).  \n\nAntonella Roccuzzo, born\u202f26\u202fFebruary\u202f1988 in Rosario, runs a fashion and lifestyle brand and often appears with Messi at public events and charitable functions."], "latencies": [4.5473713874816895, 2.550793409347534, 3.7018089294433594]}, {"question_id": "9219-4", "question": "did he service time in prison?", "turn": 4, "answer": "no", "answer_text": "no", "completed_question": "Did the soccer player Lionel Messi serve time in jail?", "given_answers": ["No. Lionel\u202fMessi has never served time in prison. Throughout his career he has faced legal matters\u2014most notably a 2016 tax\u2011fraud case in Spain\u2014but those issues were resolved through fines and settlements, not incarceration. He was convicted of tax evasion in 2016, ordered to pay a multimillion\u2011euro fine, and later received a suspended prison sentence, which means he did not actually go to jail.", "No.\u202fLionel\u202fMessi has never served a term in prison.\n\nThe closest he has come to a legal penalty was a **tax\u2011evasion case in Spain**:\n\n| Year | Charge | Verdict | Sentence |\n|------|--------|---------|----------|\n| 2016 | Defrauding the Spanish tax authorities of about \u20ac4.1\u202fmillion by using offshore companies to hide image\u2011rights earnings | Guilty (both Messi and his father, Jorge Messi) | 21\u202fmonths in prison **suspended** (i.e., no actual jail time), plus a \u20ac2\u202fmillion fine for each of them |\n\nBecause the prison term was suspended, Messi did **not** spend any time behind bars. Since then, he has complied with the court\u2011ordered payments and has not faced any further criminal convictions.", "No. Lionel\u202fMessi has never served time in prison.\n\nHe was **convicted in 2016** by a Spanish court for **tax evasion** related to image\u2011rights earnings through his company\u202fBar\u00e7a\u202fPlayers. The court sentenced him to **21\u202fmonths in prison**, but the sentence was **suspended** (i.e., he did not have to go to jail) and he was instead fined \u20ac\u200b2\u202fmillion, along with his former agent and a former club accountant. The suspended term means the conviction stands on his record, but he never actually served any custodial time."], "latencies": [3.4749248027801514, 2.7232420444488525, 4.682031631469727]}]}]